main.py
test/__init__.py
test/test_retriver.py
utilities/__init__.py
utilities/utilities.py
cif_retriever-1.0.0.dist-info/LICENSE
cif_retriever-1.0.0.dist-info/METADATA
cif_retriever-1.0.0.dist-info/WHEEL
cif_retriever-1.0.0.dist-info/entry_points.txt
cif_retriever-1.0.0.dist-info/top_level.txt
cif_retriever-1.0.0.dist-info/RECORD
