Metadata-Version: 2.1
Name: cif-retriever
Version: 1.0.0
Summary: CIF file retriever form pymatgen
Home-page: https://github.com/AlexiLJ/CIFretriver
Author: O.L.
Author-email: leiko.oleksandr@gmail.com
License: UNKNOWN
Platform: UNKNOWN
Classifier: License :: OSI Approved :: MIT License
Classifier: Programming Language :: Python :: 3
Classifier: Programming Language :: Python :: 3.6
Classifier: Programming Language :: Python :: 3.7
Classifier: Programming Language :: Python :: 3.8
Classifier: Programming Language :: Python :: 3.9
Classifier: Programming Language :: Python :: 3 :: Only
Requires-Python: >=3.6
License-File: LICENSE
Requires-Dist: pandas
Requires-Dist: pymatgen
Requires-Dist: pytest
